{
    "__mpe_config_reward": {
        "__mpe_code": {
            "prefix": "",
            "filename": "reward",
            "version": "v0.5.3"
        }
    },
    "奖励领取": {
        "recognition": {
            "type": "DirectHit",
            "param": {}
        },
        "action": {
            "type": "DoNothing",
            "param": {}
        },
        "__mpe_code": {
            "position": {
                "x": -286,
                "y": 2432
            }
        },
        "next": [
            "奖励领取任务分发"
        ],
        "interrupt": [
            "任务执行前检查"
        ]
    },
    "__mpe_external_任务执行前检查_reward": {
        "__mpe_code": {
            "position": {
                "x": 142,
                "y": 2694
            }
        }
    },
    "奖励领取任务分发": {
        "recognition": {
            "type": "DirectHit",
            "param": {}
        },
        "action": {
            "type": "DoNothing",
            "param": {}
        },
        "__mpe_code": {
            "position": {
                "x": 154,
                "y": 2438
            }
        },
        "interrupt": [
            "友情点赠送",
            "邮件领取",
            "任务领取",
            "通行证领取_副本",
            "防御基地奖励领取",
            "启用奖励领取任务完成节点"
        ],
        "next": [
            "奖励领取任务完成"
        ]
    },
    "友情点赠送": {
        "recognition": {
            "type": "TemplateMatch",
            "param": {
                "template": [
                    "common/小红点.png"
                ],
                "roi": [
                    1245,
                    145,
                    27,
                    27
                ],
                "green_mask": true
            }
        },
        "action": {
            "type": "Click",
            "param": {
                "target": [
                    1232,
                    160,
                    23,
                    24
                ]
            }
        },
        "focus": "开始友情点赠送任务",
        "__mpe_code": {
            "position": {
                "x": 643,
                "y": 2300
            }
        },
        "next": [
            "赠送友情点"
        ]
    },
    "邮件领取": {
        "recognition": {
            "type": "TemplateMatch",
            "param": {
                "template": [
                    "common/小红点.png"
                ],
                "roi": [
                    1210,
                    8,
                    32,
                    29
                ],
                "green_mask": true
            }
        },
        "action": {
            "type": "Click",
            "param": {
                "target": [
                    1216,
                    15,
                    20,
                    19
                ]
            }
        },
        "focus": "开始邮件领取任务",
        "__mpe_code": {
            "position": {
                "x": 647,
                "y": 2561
            }
        },
        "next": [
            "邮件领取完毕"
        ],
        "interrupt": [
            "领取邮件"
        ]
    },
    "启用奖励领取任务完成节点": {
        "recognition": {
            "type": "DirectHit",
            "param": {}
        },
        "action": {
            "type": "Custom",
            "param": {
                "custom_action": "NodeOverride",
                "custom_action_param": {
                    "奖励领取任务完成": {
                        "threshold": "0.7"
                    }
                }
            }
        },
        "focus": "启用奖励领取任务完成节点",
        "__mpe_code": {
            "position": {
                "x": 638,
                "y": 4448
            }
        }
    },
    "赠送友情点": {
        "recognition": {
            "type": "OCR",
            "param": {
                "expected": [
                    "赠送"
                ],
                "roi": [
                    529,
                    570,
                    311,
                    89
                ]
            }
        },
        "action": {
            "type": "Click",
            "param": {}
        },
        "__mpe_code": {
            "position": {
                "x": 927,
                "y": 2149
            }
        },
        "next": [
            "确定赠送友情点"
        ]
    },
    "确定赠送友情点": {
        "recognition": {
            "type": "OCR",
            "param": {
                "expected": [
                    "确认"
                ],
                "roi": [
                    524,
                    396,
                    236,
                    116
                ]
            }
        },
        "action": {
            "type": "Click",
            "param": {}
        },
        "post_delay": 400,
        "__mpe_code": {
            "position": {
                "x": 1242,
                "y": 2194
            }
        },
        "next": [
            "关闭友情点赠送页面"
        ]
    },
    "关闭友情点赠送页面": {
        "recognition": {
            "type": "OCR",
            "param": {
                "expected": [
                    "好友"
                ],
                "roi": [
                    577,
                    54,
                    126,
                    67
                ]
            }
        },
        "action": {
            "type": "Click",
            "param": {
                "target": [
                    778,
                    70,
                    42,
                    37
                ]
            }
        },
        "__mpe_code": {
            "position": {
                "x": 1507,
                "y": 2224
            }
        },
        "next": [
            "友情点赠送完毕"
        ]
    },
    "领取邮件": {
        "recognition": {
            "type": "OCR",
            "param": {
                "roi": [
                    583,
                    582,
                    257,
                    68
                ],
                "expected": [
                    "全部领取"
                ]
            }
        },
        "action": {
            "type": "Click",
            "param": {}
        },
        "__mpe_code": {
            "position": {
                "x": 1072,
                "y": 2692
            }
        },
        "next": [
            "点击领取奖励"
        ]
    },
    "__mpe_external_点击领取奖励_reward": {
        "__mpe_code": {
            "position": {
                "x": 2651,
                "y": 3261
            }
        }
    },
    "任务领取": {
        "recognition": {
            "type": "TemplateMatch",
            "param": {
                "template": [
                    "common/小红点.png"
                ],
                "roi": [
                    1094,
                    46,
                    44,
                    44
                ],
                "green_mask": true
            }
        },
        "action": {
            "type": "Click",
            "param": {
                "target": [
                    1105,
                    60,
                    17,
                    21
                ]
            }
        },
        "focus": "开始任务领取任务",
        "__mpe_code": {
            "position": {
                "x": 637,
                "y": 2815
            }
        },
        "next": [
            "关闭任务面板"
        ],
        "interrupt": [
            "检查任务领取项"
        ]
    },
    "关闭任务面板": {
        "recognition": {
            "type": "ColorMatch",
            "param": {
                "lower": [
                    120,
                    120,
                    120
                ],
                "upper": [
                    130,
                    130,
                    130
                ],
                "method": 4,
                "roi": [
                    744,
                    626,
                    35,
                    19
                ]
            }
        },
        "action": {
            "type": "Click",
            "param": {
                "target": [
                    798,
                    41,
                    19,
                    17
                ]
            }
        },
        "__mpe_code": {
            "position": {
                "x": 1632,
                "y": 2828
            }
        },
        "next": [
            "任务领取完毕"
        ]
    },
    "检查任务领取项": {
        "recognition": {
            "type": "ColorMatch",
            "param": {
                "lower": [
                    0,
                    170,
                    240
                ],
                "upper": [
                    70,
                    190,
                    255
                ],
                "method": 4,
                "roi": [
                    744,
                    626,
                    35,
                    19
                ]
            }
        },
        "action": {
            "type": "Click",
            "param": {
                "target": [
                    722,
                    635,
                    81,
                    24
                ]
            }
        },
        "__mpe_code": {
            "position": {
                "x": 1240,
                "y": 2907
            }
        },
        "next": [
            "检查任务领取项",
            "关闭任务面板"
        ],
        "interrupt": [
            "点击领取奖励"
        ]
    },
    "任务领取完毕": {
        "recognition": {
            "type": "DirectHit",
            "param": {}
        },
        "action": {
            "type": "DoNothing",
            "param": {}
        },
        "__mpe_code": {
            "position": {
                "x": 2009,
                "y": 2730
            }
        }
    },
    "友情点赠送完毕": {
        "recognition": {
            "type": "DirectHit",
            "param": {}
        },
        "action": {
            "type": "DoNothing",
            "param": {}
        },
        "__mpe_code": {
            "position": {
                "x": 1792,
                "y": 2256
            }
        }
    },
    "选择通行证": {
        "recognition": {
            "type": "TemplateMatch",
            "param": {
                "template": [
                    "common/小红点.png"
                ],
                "roi": [
                    1227,
                    71,
                    52,
                    231
                ],
                "green_mask": true,
                "index": 0
            }
        },
        "action": {
            "type": "Click",
            "param": {}
        },
        "post_wait_freezes": 1000,
        "__mpe_code": {
            "position": {
                "x": 1007,
                "y": 3551
            }
        },
        "next": [
            "当前通行证领取完成"
        ],
        "interrupt": [
            "有未领取通行证任务",
            "通行证升级",
            "有未领取通行证奖励"
        ]
    },
    "进入通行证任务": {
        "recognition": {
            "type": "OCR",
            "param": {
                "expected": [
                    "任务"
                ],
                "roi": [
                    465,
                    215,
                    352,
                    37
                ]
            }
        },
        "action": {
            "type": "Click",
            "param": {}
        },
        "post_wait_freezes": 1000,
        "__mpe_code": {
            "position": {
                "x": 1730,
                "y": 3611
            }
        },
        "next": [
            "通行证任务全部领取"
        ]
    },
    "进入通行证奖励": {
        "recognition": {
            "type": "OCR",
            "param": {
                "expected": [
                    "奖励"
                ],
                "roi": [
                    465,
                    215,
                    352,
                    37
                ]
            }
        },
        "action": {
            "type": "Click",
            "param": {}
        },
        "post_wait_freezes": 1000,
        "__mpe_code": {
            "position": {
                "x": 1718,
                "y": 3875
            }
        },
        "next": [
            "通行证奖励全部领取"
        ]
    },
    "通行证任务全部领取": {
        "recognition": {
            "type": "OCR",
            "param": {
                "expected": [
                    "全部领取"
                ],
                "roi": [
                    517,
                    645,
                    253,
                    52
                ]
            }
        },
        "action": {
            "type": "Click",
            "param": {}
        },
        "post_wait_freezes": 1000,
        "__mpe_code": {
            "position": {
                "x": 2073,
                "y": 3599
            }
        }
    },
    "通行证奖励全部领取": {
        "recognition": {
            "type": "OCR",
            "param": {
                "expected": [
                    "全部领取"
                ],
                "roi": [
                    517,
                    645,
                    253,
                    52
                ]
            }
        },
        "action": {
            "type": "Click",
            "param": {}
        },
        "post_wait_freezes": 1000,
        "__mpe_code": {
            "position": {
                "x": 2022,
                "y": 3947
            }
        },
        "next": [
            "点击领取奖励"
        ]
    },
    "通行证升级": {
        "recognition": {
            "type": "OCR",
            "param": {
                "expected": [
                    "RANK"
                ],
                "roi": [
                    588,
                    317,
                    100,
                    35
                ]
            }
        },
        "action": {
            "type": "Click",
            "param": {
                "target": [
                    564,
                    486,
                    185,
                    104
                ]
            }
        },
        "__mpe_code": {
            "position": {
                "x": 1410,
                "y": 3710
            }
        }
    },
    "当前通行证领取完成": {
        "recognition": {
            "type": "TemplateMatch",
            "param": {
                "roi": [
                    455,
                    193,
                    373,
                    115
                ],
                "template": [
                    "common/小红点.png"
                ],
                "green_mask": true
            }
        },
        "action": {
            "type": "Click",
            "param": {
                "target": [
                    796,
                    42,
                    18,
                    17
                ]
            }
        },
        "inverse": true,
        "__mpe_code": {
            "position": {
                "x": 1933,
                "y": 3322
            }
        }
    },
    "有未领取通行证任务": {
        "recognition": {
            "type": "TemplateMatch",
            "param": {
                "template": [
                    "common/小红点.png"
                ],
                "roi": [
                    775,
                    175,
                    85,
                    75
                ],
                "green_mask": true
            }
        },
        "action": {
            "type": "DoNothing",
            "param": {}
        },
        "__mpe_code": {
            "position": {
                "x": 1428,
                "y": 3634
            }
        },
        "next": [
            "进入通行证任务"
        ]
    },
    "有未领取通行证奖励": {
        "recognition": {
            "type": "TemplateMatch",
            "param": {
                "roi": [
                    592,
                    203,
                    52,
                    46
                ],
                "template": [
                    "common/小红点1.png"
                ],
                "green_mask": true
            }
        },
        "action": {
            "type": "DoNothing",
            "param": {}
        },
        "__mpe_code": {
            "position": {
                "x": 1468,
                "y": 3910
            }
        },
        "next": [
            "进入通行证奖励"
        ]
    },
    "所有通行证领取完毕": {
        "recognition": {
            "type": "TemplateMatch",
            "param": {
                "template": [
                    "common/小红点.png"
                ],
                "roi": [
                    1227,
                    71,
                    52,
                    231
                ],
                "green_mask": true,
                "index": 0
            }
        },
        "action": {
            "type": "Custom",
            "param": {
                "custom_action": "DisableNode",
                "custom_action_param": {
                    "node_name": "通行证领取"
                }
            }
        },
        "inverse": true,
        "__mpe_code": {
            "position": {
                "x": 979,
                "y": 3171
            }
        },
        "next": [
            "退出通行证选择页面"
        ]
    },
    "退出通行证选择页面": {
        "recognition": {
            "type": "DirectHit",
            "param": {}
        },
        "action": {
            "type": "Click",
            "param": {
                "target": [
                    1092,
                    110,
                    22,
                    20
                ]
            }
        },
        "__mpe_code": {
            "position": {
                "x": 1455,
                "y": 3236
            }
        }
    },
    "邮件领取完毕": {
        "recognition": {
            "type": "ColorMatch",
            "param": {
                "lower": [
                    150,
                    150,
                    150
                ],
                "upper": [
                    160,
                    160,
                    160
                ],
                "method": 4,
                "roi": [
                    767,
                    590,
                    33,
                    38
                ]
            }
        },
        "action": {
            "type": "Click",
            "param": {
                "target": [
                    786,
                    85,
                    21,
                    22
                ]
            }
        },
        "__mpe_code": {
            "position": {
                "x": 1084,
                "y": 2422
            }
        }
    },
    "防御基地奖励领取": {
        "recognition": {
            "type": "TemplateMatch",
            "param": {
                "template": [
                    "common/小红点1.png"
                ],
                "green_mask": true,
                "roi": [
                    387,
                    544,
                    58,
                    63
                ]
            }
        },
        "action": {
            "type": "Click",
            "param": {
                "target": [
                    325,
                    589,
                    73,
                    37
                ]
            }
        },
        "post_wait_freezes": 1000,
        "__mpe_code": {
            "position": {
                "x": 605,
                "y": 3741
            }
        },
        "next": [
            "获得防御基地奖励"
        ],
        "interrupt": [
            "存在免费一举歼灭",
            "启用获得防御基地奖励节点"
        ]
    },
    "存在免费一举歼灭": {
        "recognition": {
            "type": "TemplateMatch",
            "param": {
                "template": [
                    "common/小红点.png"
                ],
                "roi": [
                    610,
                    577,
                    44,
                    37
                ],
                "green_mask": true
            }
        },
        "action": {
            "type": "DoNothing",
            "param": {}
        },
        "__mpe_code": {
            "position": {
                "x": 981,
                "y": 4320
            }
        },
        "next": [
            "一举歼灭"
        ]
    },
    "一举歼灭": {
        "recognition": {
            "type": "OCR",
            "param": {
                "expected": [
                    "举歼灭"
                ],
                "roi": [
                    418,
                    542,
                    269,
                    133
                ]
            }
        },
        "action": {
            "type": "Click",
            "param": {}
        },
        "__mpe_code": {
            "position": {
                "x": 1225,
                "y": 4332
            }
        },
        "next": [
            "进行歼灭"
        ]
    },
    "进行歼灭": {
        "recognition": {
            "type": "OCR",
            "param": {
                "expected": [
                    "进行歼灭"
                ],
                "roi": [
                    537,
                    476,
                    313,
                    143
                ]
            }
        },
        "action": {
            "type": "Click",
            "param": {}
        },
        "post_wait_freezes": 600,
        "__mpe_code": {
            "position": {
                "x": 1467,
                "y": 4317
            }
        },
        "next": [
            "退出一举歼灭"
        ],
        "interrupt": [
            "点击领取奖励"
        ]
    },
    "防御基地奖励领取完毕": {
        "recognition": {
            "type": "DirectHit",
            "param": {}
        },
        "action": {
            "type": "Custom",
            "param": {
                "custom_action": "DisableNode",
                "custom_action_param": {
                    "node_name": "防御基地奖励领取"
                }
            }
        },
        "__mpe_code": {
            "position": {
                "x": 1595,
                "y": 4106
            }
        },
        "next": [
            "点击领取奖励"
        ]
    },
    "退出一举歼灭": {
        "recognition": {
            "type": "OCR",
            "param": {
                "expected": [
                    "取消"
                ],
                "roi": [
                    452,
                    501,
                    170,
                    102
                ]
            }
        },
        "action": {
            "type": "Click",
            "param": {}
        },
        "__mpe_code": {
            "position": {
                "x": 1813,
                "y": 4302
            }
        },
        "next": [
            "启用获得防御基地奖励节点"
        ]
    },
    "获得防御基地奖励": {
        "recognition": {
            "type": "OCR",
            "param": {
                "expected": [
                    "获得奖励"
                ],
                "roi": [
                    631,
                    575,
                    177,
                    79
                ]
            }
        },
        "action": {
            "type": "Click",
            "param": {}
        },
        "enabled": false,
        "__mpe_code": {
            "position": {
                "x": 981,
                "y": 3975
            }
        },
        "next": [
            "防御基地奖励领取完毕"
        ]
    },
    "启用获得防御基地奖励节点": {
        "recognition": {
            "type": "DirectHit",
            "param": {}
        },
        "action": {
            "type": "Custom",
            "param": {
                "custom_action": "EnableNode",
                "custom_action_param": "获得防御基地奖励"
            }
        },
        "__mpe_code": {
            "position": {
                "x": 2075,
                "y": 4180
            }
        }
    },
    "通行证领取_副本": {
        "recognition": {
            "type": "TemplateMatch",
            "param": {
                "template": [
                    "common/小红点1.png"
                ],
                "roi": [
                    1119,
                    88,
                    49,
                    65
                ],
                "green_mask": true
            }
        },
        "action": {
            "type": "Click",
            "param": {
                "target_offset": [
                    -10,
                    10,
                    0,
                    0
                ]
            }
        },
        "focus": "开始通行证领取任务",
        "post_wait_freezes": 1000,
        "__mpe_code": {
            "position": {
                "x": 630,
                "y": 3097
            }
        },
        "interrupt": [
            "选择通行证"
        ],
        "next": [
            "所有通行证领取完毕"
        ]
    },
    "奖励领取任务完成": {
        "recognition": {
            "type": "TemplateMatch",
            "param": {
                "template": [
                    "shop/百货商店按钮.png"
                ],
                "green_mask": true,
                "threshold": [
                    1
                ],
                "roi": [
                    269,
                    406,
                    219,
                    134
                ]
            }
        },
        "action": {
            "type": "DoNothing",
            "param": {}
        },
        "focus": "奖励领取任务完成",
        "__mpe_code": {
            "position": {
                "x": 659,
                "y": 2004
            }
        }
    }
}